README.md
setup.py
oopgrade/__init__.py
oopgrade/cli.py
oopgrade/data.py
oopgrade/log.py
oopgrade/oopgrade.py
oopgrade/pubsub.py
oopgrade/utils.py
oopgrade/version.py
oopgrade.egg-info/PKG-INFO
oopgrade.egg-info/SOURCES.txt
oopgrade.egg-info/dependency_links.txt
oopgrade.egg-info/entry_points.txt
oopgrade.egg-info/requires.txt
oopgrade.egg-info/top_level.txt
spec/__init__.py
spec/data_migration_spec.py
spec/version_spec.py
spec/fixtures/__init__.py