Metadata-Version: 2.1
Name: oopgrade
Version: 0.21.0
Summary: Upgrade and migration tools
Home-page: https://github.com/gisce/oopgrade
Author: GISCE-TI, S.L.
Author-email: devel@gisce.net
License: AGPL-3
Platform: UNKNOWN
